itk/AdaptiveDenoisingPython.py
itk/itkVarianceImageFilterPython.py
itk/_AdaptiveDenoisingPython.so
itk/itkAdaptiveNonLocalMeansDenoisingImageFilterPython.py
itk/itkNonLocalPatchBasedImageFilterPython.py
itk/Configuration/AdaptiveDenoisingConfig.py
itk/Configuration/AdaptiveDenoising_snake_case.py
itk_adaptivedenoising-0.2.0.dist-info/WHEEL
itk_adaptivedenoising-0.2.0.dist-info/METADATA
itk_adaptivedenoising-0.2.0.dist-info/top_level.txt
itk_adaptivedenoising-0.2.0.dist-info/RECORD
itk_adaptivedenoising-0.2.0.dist-info/LICENSE
